LICENSE
MANIFEST.in
README.md
README.rst
RELEASE-VERSION
itest.sh
setup.py
version.py
coordinate/__init__.py
coordinate/base_client.py
coordinate/constants.py
coordinate/coordinatec.py
coordinate/exceptions.py
coordinate/fifolock.py
coordinate/heapq.py
coordinate/job_client.py
coordinate/job_httpd.py
coordinate/job_server.py
coordinate/job_sqlite.py
coordinate/postgres_work_spec.py
coordinate/run.py
coordinate/run_multi_worker.py
coordinate/server.py
coordinate/server_work_unit.py
coordinate/sqlite_work_spec.py
coordinate/summary_stats.py
coordinate/work_spec.py
coordinate/workers.py
coordinate/workunit_run.py
coordinate/zopen.py
coordinate.egg-info/PKG-INFO
coordinate.egg-info/SOURCES.txt
coordinate.egg-info/dependency_links.txt
coordinate.egg-info/entry_points.txt
coordinate.egg-info/requires.txt
coordinate.egg-info/top_level.txt
coordinate/tests/__init__.py
coordinate/tests/test_client_retry.py
coordinate/tests/test_fifolock.py
coordinate/tests/test_job.py
coordinate/tests/test_job_client.py
coordinate/tests/test_job_flow.py
coordinate/tests/test_postgres_work_spec.py
coordinate/tests/test_rejester_worker.py
coordinate/tests/test_server.py
coordinate/tests/test_sqliteworkspec.py
coordinate/tests/test_task_master.py