Metadata-Version: 1.1
Name: coordinate
Version: 0.1.5
Summary: Tools for large scale data clustering.
Home-page: http://github.com/diffeo/coordinate
Author: Diffeo, Inc.
Author-email: support@diffeo.com
License: MIT/X11 license http://opensource.org/licenses/MIT
Platform: UNKNOWN
Classifier: Development Status :: 3 - Alpha
Classifier: Topic :: Utilities
Classifier: License :: OSI Approved :: MIT License
